Metadata-Version: 1.0
Name: distributions-fou-foo
Version: 0.1
Summary: udacity-exercise
Home-page: UNKNOWN
Author: J. Antonio García
Author-email: jose.ramirez@cimat.mx
License: UNKNOWN
Platform: UNKNOWN
